MANIFEST.in
README.txt
setup.cfg
setup.py
Searchpy.egg-info/PKG-INFO
Searchpy.egg-info/SOURCES.txt
Searchpy.egg-info/dependency_links.txt
Searchpy.egg-info/not-zip-safe
Searchpy.egg-info/requires.txt
Searchpy.egg-info/top_level.txt
searchpy/__init__.py
searchpy/search.py
searchpy/utilities.py
searchpy/adapters/__init__.py
searchpy/adapters/bing.py
searchpy/adapters/google.py
tests/__init__.py
tests/test_search.py
tests/test_utilities.py