Metadata-Version: 1.0
Name: Searchpy
Version: 1.4.3
Summary: A google interface library
Home-page: http://bitbucket.org/ixmatus/searchpy
Author: Parnell Springmeyer
Author-email: ixmatus@gmail.com
License: PSF
Platform: UNKNOWN
Classifier: Intended Audience :: Developers
Classifier: License :: OSI Approved :: Python Software Foundation License
Classifier: Programming Language :: Python
Classifier: Topic :: Software Development :: Libraries :: Python Modules
